[{"track_id": "TRAMWIH128F92D28B2", "tempo": "94.301", "duration": "162.58567", "artist_7digitalid": "62870", "artist_familiarity": "0.2287303097845054", "artist_hotttnesss": "0.0", "artist_id": "ARRCDBV12454A42B90", "artist_name": "Manolis Famellos & I Podilates", "release": "Manolis Famellos & I Podilates + 5 Anekdota Tragoudia", "release_7digitalid": "425865", "song_hotttnesss": "nan", "song_id": "SONHTWP12A8C142744", "title": "Vals '89", "track_7digitalid": "4752435", "artist_terms": {"greek": 1.0}, "similar_artists": ["ARLLHRV11F4C844C25", "ARTEIFZ1269FCD82FB", "ARJILXU11F4C84805C", "AROYBXY12509411F28", "AROGFER12509411F20", "ARDLYRS11F4C844C0A", "ARNZFAP12509411DA0", "ARFMOCC12509411F2F", "ARVISHQ11F4C84802F", "ARYMMBD12454A432CA", "ARV9SMG1187B9A17FE", "ARWKVPA12509411EFF", "ARWKVBH1257509B46E", "ARXLCDE12509411F24", "ARZBDOR1269FB37A10", "ARZEQRM1269FB30E41", "ARZFMFM1269FB34B58", "ARZQJZF1269FB34D43", "ARZSHVB1269FB2E127", "ARZSHVM1269FB32A95", "ARZXTUO12509411DAE", "AR3AXMK11C8A416BA4", "AR4FH1O11A348F0940", "ARAGVVQ11F4C844C02", "ARBHPXV11A348F0946", "ARBKMHZ11F4C843491", "ARBPOCR1269FB26DAC", "ARBTBZC125094131FF", "ARBZCHB1269FB26B30", "ARCHEOW11F4C843483", "ARCHJLD1269FB26DAB", "ARCRNVV1269FCD5B9C", "ARYNYOP1264D13A3F3", "ARDWLIL11F4C84348C", "ARDY4PK1187FB4F865", "ARDZLFU12509400062", "AREBSCJ1241B9C7BDF", "AREJJAC11F4C843482", "AREPVCX1242077F23C", "ARGBYKD1269FCD57B7", "ARGHWHT1264D134F80", "ARGOAMH11F4C844C07", "ARGSOKS12509411F37", "ARVNXSM11F4C843506", "ARDRQOR11F4C844DA4", "ARHEPGM12509411FB7", "ARHMUJK1250940F0DE", "ARHNNXB11F4C843485", "ARHP1WV11C8A42B616", "ARINMKR11F4C843487", "ARJAPSI1241B9CC5B3", "ARJAXQM12509411F7F", "ARKOZAR1250940B7D8", "ARKTTCY1269FB34D4C", "ARKWWXR12509411EF6", "ARLIUIR11F4C8434D8", "ARLLQZO1264D13038D", "ARLPGFB1269FB30E3E", "ARLZYN01187B9976B2", "ARL95DA1187FB3EA0E", "ARMNISR11F4C843488", "ARMXYGA1250940F33E", "ARNRAEC11F4C843492", "ARNRXSK11F4C843484", "AROEI7Y11A348F0944", "AROPSFY11F4C843527", "ARDBWEC1250940F214", "AROT1KE1187B98B4B3", "AROW8WS1187B9A99D5", "ARYXBCS1250940B844", "ARPWMGF1269FB25878", "ARPYLPM1269FB255FF", "ARQSZLT124207825BA", "ARRCTPD11F4C84348D", "ARDNZJD11F4C844DA8", "ARRYFFM1187FB3F6EC", "ARSJMH51187FB53517", "ARSMFYG11F4C843489", "ARSLIRH11F4C844C1D", "ARTFKBK1264D13A3F2", "ARTOGWD1269FB38628", "ARTTLBK11A348F0941", "ARUDU0Y1187FB49F41", "ARUKUHQ11F4C84348A", "AR2DEHQ1187B98DE98", "ARH82SF1187FB3ED2A", "ARVRBBY12509411F75", "ARODSOF125093C8A60", "AROFOGN125094122FE", "ARRWKSQ11F4C844D66", "ARZZMAR1269FCD4838", "ARCCIIJ1269FCD4F9A", "ARYUFLV122988EEB7C", "ARVUVQH122988F0438", "ARBVXWW12454A4748E", "ARNFMOX125FEF32099", "ARRLDGK12509412082", "ARTIJUB12592CDA2BF", "ARUVBTV1269FB258F1", "ARM0OE91187FB3ED3B"]}
]