[{"track_id": "TRAIAWE128F427700F", "tempo": "84.672", "duration": "300.5122", "artist_7digitalid": "197693", "artist_familiarity": "0.021666446173679545", "artist_hotttnesss": "0.0", "artist_id": "ARWQGYW11F4C846BF2", "artist_name": "Yodi's", "release": "Z\u00e8l\u00e9", "release_7digitalid": "257891", "song_hotttnesss": "nan", "song_id": "SOIAMVN12A8C13B750", "title": "Z\u00e9l\u00e9", "track_7digitalid": "2904430", "artist_terms": {"ghetto tech": 1.0, "house": 0.686121369849528}, "similar_artists": ["ARXEOQM1242077EFC3", "ARWAQOE1241B9CB568", "ARWPHDF1242077F0B8", "ARXLYEC12802FDD7DC", "ARYAVHL1241B9CC542", "ARWDBVV12420781EE1", "ARIDCWU12420780B10", "ARDEJZA12AA0D8C1E7", "AROBWBC1264D13A97E", "ARPJHWK11F50C4E83B", "ARQQRJI11F4C8416BC", "ARSBFGV1241B9CE441", "ARSSLTP1241B9CC51A", "ARTMUFH12454A4CB91", "ARBYTDZ1241B9C7959", "ARCWDWM11F4C843763", "ARKUDRV1241B9C4453", "ARPYGTL12420781B75", "ARHZNMA1264D1329A1", "ARXZ5KO1187B988C72", "ARZYHXU1250941471A", "ARINIKT11F50C4878F", "ARKCA421187FB55364", "ARRZKZN1187FB39640", "ARBOTVT11F50C51362", "ARKSJDD12592CD9D7E", "ARMJTYS1257509DE8D", "ARHMQHN1241B9C56C8", "ARWHIXW12086C14FCC", "ARZPHZW12454A2E275", "AROREOI1242077FB5B", "ARARXUG12454A2DA91", "ARPZPET1252CCF9386", "ARRWIBO12802FDD653", "ARGPNNA11E2835EE66", "AR1YVIA1187FB4BECF", "ARAUCFP1241B9C6BB0", "ARBHNBT12420782398", "ARDJENS11EB9C80B6B", "ARIFGTV11F4C842EBC", "ARHVZFT1242078074A", "ARUBFXX1241B9C66CA", "ARVAGCT1241B9C49B9", "ARUDHZV1269FCD0C4C", "ARWMEGA1241B9C7B35", "ARVVIVB11F4C83BD8C", "ARXZFWQ1257509C111", "ARZAUXL1241B9C72A7", "ARZLXEW1241B9CA2B4", "ARZTOED11F50C4AA80", "ARZUXJU11EBCD7B515", "ARAWQOP11F50C4B221", "ARBGEZH1241B9CC714", "ARBLTGF1242078040F", "ARBTDDX1250941633A", "ARBWQLR124207831A9", "ARCMDDJ11EBCD77112", "ARDOTIO1242077E48F", "ARDPCXE12592CDA2AB", "ARDQQOT1241B9CA2B5", "ARDVPCR1257509E054", "ARDZCCK122988FCF7E", "ARD4ZIT119B86678B3", "AREHMNU1250940B9F1", "ARCXLYN1241B9C4BF4", "ARFBIU31187FB57F28", "ARFWVRK11E2835D8F8", "ARGIOIA12454A4D798", "ARUXYTH1252CCF95B4", "ARHYDUB1241B9C7E30", "ARICCAY12420783608", "ARIDXAL12472CE2FCB", "ARIDXDO1264D13715D", "ARIMDDT1269FB375AA", "ARJJICF1264D1300B3", "ARJQREV1252CCF912C", "ARJSNFT1241B9CA71D", "ARKGPXP11F50C4B98E", "ARKTKIO12420782EA5", "ARKVJVN11EBCD78F93", "ARLSUAA1241B9CD265", "ARLQOEC1257509DAAC", "ARLSSXW12802FDD811", "ARGWHXA1250940F9B6", "AREPOUG11F4C83D36C", "ARLYXRI11F4C84743F", "ARWOKOL1269FCD9037", "ARGYTVO127D395D52F", "ARDDKRR123DEF5D5B0", "ARZYKKB1257509EA7F", "ARFBYWR1187FB42C1F", "ARMGFRS1242078356C", "ARBXU4B1187FB37FF6", "ARMQFAK1257509B26D", "ARMWKHG1241B9C7FF6", "ARWYAQY12420780A0A", "ARNLFCB12802FDE522", "AREDYIK1241B9CA9C3", "ARZLDCI11F50C4A001", "AROTMHP1252CCF9E33"]}
]